{
  "discountCodes": [
    {
      "code": "X2JY7ZL",
      "isUsed": false,
      "discountPercentage": 0.15,
      "validUntil": "023-12-31T23:59:59.999Z"
    },
    {
      "code": "G5Q38DK",
      "isUsed": false,
      "discountPercentage": 0.15,
      "validUntil": "023-12-31T23:59:59.999Z"
    },
    {
      "code": "R9T7WNX",
      "isUsed": false,
      "discountPercentage": 0.15,
      "validUntil": "023-12-31T23:59:59.999Z"
    },
    {
      "code": "A6K4B3H",
      "isUsed": false,
      "discountPercentage": 0.15,
      "validUntil": "023-12-31T23:59:59.999Z"
    },
    {
      "code": "P1V9SCW",
      "isUsed": false,
      "discountPercentage": 0.15,
      "validUntil": "023-12-31T23:59:59.999Z"
    },
    {
      "code": "M8D5Y2R",
      "isUsed": false,
      "discountPercentage": 0.15,
      "validUntil": "023-12-31T23:59:59.999Z"
    },
    {
      "code": "F3H6B9J",
      "isUsed": false,
      "discountPercentage": 0.15,
      "validUntil": "023-12-31T23:59:59.999Z"
    },
    {
      "code": "L7N4WXV",
      "isUsed": false,
      "discountPercentage": 0.15,
      "validUntil": "023-12-31T23:59:59.999Z"
    },
    {
      "code": "C2G9K6P",
      "isUsed": false,
      "discountPercentage": 0.15,
      "validUntil": "023-12-31T23:59:59.999Z"
    },
    {
      "code": "U4E1R3M",
      "isUsed": false,
      "discountPercentage": 0.15,
      "validUntil": "023-12-31T23:59:59.999Z"
    },
    {
      "code": "V9Z7L6Q",
      "isUsed": false,
      "discountPercentage": 0.15,
      "validUntil": "023-12-31T23:59:59.999Z"
    },
    {
      "code": "D5S2W1H",
      "isUsed": false,
      "discountPercentage": 0.15,
      "validUntil": "023-12-31T23:59.999Z"
    },
    {
        "code": "T8R9B6J",
        "isUsed": false,
        "discountPercentage": 0.15,
        "validUntil": "023-12-31T23:59.999Z"
      },
      {
        "code": "K6P3CXN",
        "isUsed": false,
        "discountPercentage": 0.15,
        "validUntil": "023-12-31T23:59.999Z"
      },
      {
        "code": "B2H7G4F",
        "isUsed": false,
        "discountPercentage": 0.15,
        "validUntil": "023-12-31T23:59.999Z"
      },
      {
        "code": "N4X1M6S",
        "isUsed": false,
        "discountPercentage": 0.15,
        "validUntil": "023-12-31T23:59.999Z"
      },
      {
        "code": "W9Q7J3V",
        "isUsed": false,
        "discountPercentage": 0.15,
        "validUntil": "023-12-31T23:59.999Z"
      },
      {
        "code": "Y3R6N2L",
        "isUsed": false,
        "discountPercentage": 0.15,
        "validUntil": "023-12-31T23:59.999Z"
      },
      {
        "code": "S6F8K4D",
        "isUsed": false,
        "discountPercentage": 0.15,
        "validUntil": "023-12-31T23:59.999Z"
      },
      {
        "code": "E1V9W3J",
        "isUsed": false,
        "discountPercentage": 0.15,
        "validUntil": "023-12-31T23:59.999Z"
      }

      



      
}
